[
null,
{"id":1,"list":[{"code":122,"indent":0,"parameters":[1,20,0,2,1,20]},{"code":111,"indent":0,"parameters":[1,1,0,5,3]},{"code":111,"indent":1,"parameters":[1,1,0,10,3]},{"code":111,"indent":2,"parameters":[1,1,0,15,3]},{"code":250,"indent":3,"parameters":[{"name":"mad1","volume":15,"pitch":110,"pan":0}]},{"code":0,"indent":3,"parameters":[]},{"code":411,"indent":2,"parameters":[]},{"code":250,"indent":3,"parameters":[{"name":"mad1","volume":15,"pitch":100,"pan":0}]},{"code":0,"indent":3,"parameters":[]},{"code":412,"indent":2,"parameters":[]},{"code":121,"indent":2,"parameters":[3,3,1]},{"code":0,"indent":2,"parameters":[]},{"code":411,"indent":1,"parameters":[]},{"code":250,"indent":2,"parameters":[{"name":"mad1","volume":15,"pitch":90,"pan":0}]},{"code":0,"indent":2,"parameters":[]},{"code":412,"indent":1,"parameters":[]},{"code":121,"indent":1,"parameters":[3,3,1]},{"code":0,"indent":1,"parameters":[]},{"code":411,"indent":0,"parameters":[]},{"code":250,"indent":1,"parameters":[{"name":"mad2","volume":15,"pitch":90,"pan":0}]},{"code":0,"indent":1,"parameters":[]},{"code":412,"indent":0,"parameters":[]},{"code":121,"indent":0,"parameters":[3,3,1]},{"code":122,"indent":0,"parameters":[1,20,0,2,1,20]},{"code":111,"indent":0,"parameters":[1,1,0,5,3]},{"code":111,"indent":1,"parameters":[1,1,0,10,3]},{"code":111,"indent":2,"parameters":[1,1,0,15,3]},{"code":250,"indent":3,"parameters":[{"name":"mad1","volume":20,"pitch":110,"pan":0}]},{"code":0,"indent":3,"parameters":[]},{"code":411,"indent":2,"parameters":[]},{"code":250,"indent":3,"parameters":[{"name":"mad1","volume":20,"pitch":100,"pan":0}]},{"code":0,"indent":3,"parameters":[]},{"code":412,"indent":2,"parameters":[]},{"code":121,"indent":2,"parameters":[3,3,1]},{"code":0,"indent":2,"parameters":[]},{"code":411,"indent":1,"parameters":[]},{"code":250,"indent":2,"parameters":[{"name":"mad1","volume":15,"pitch":90,"pan":0}]},{"code":0,"indent":2,"parameters":[]},{"code":412,"indent":1,"parameters":[]},{"code":121,"indent":1,"parameters":[3,3,1]},{"code":0,"indent":1,"parameters":[]},{"code":411,"indent":0,"parameters":[]},{"code":250,"indent":1,"parameters":[{"name":"mad2","volume":20,"pitch":90,"pan":0}]},{"code":0,"indent":1,"parameters":[]},{"code":412,"indent":0,"parameters":[]},{"code":121,"indent":0,"parameters":[3,3,1]},{"code":0,"indent":0,"parameters":[]}],"name":"PisoMadeira","switchId":3,"trigger":2},
{"id":2,"list":[{"code":122,"indent":0,"parameters":[1,20,0,2,1,20]},{"code":111,"indent":0,"parameters":[1,1,0,5,3]},{"code":111,"indent":1,"parameters":[1,1,0,10,3]},{"code":111,"indent":2,"parameters":[1,1,0,15,3]},{"code":250,"indent":3,"parameters":[{"name":"ter1","volume":15,"pitch":110,"pan":0}]},{"code":0,"indent":3,"parameters":[]},{"code":411,"indent":2,"parameters":[]},{"code":250,"indent":3,"parameters":[{"name":"ter1","volume":15,"pitch":100,"pan":0}]},{"code":0,"indent":3,"parameters":[]},{"code":412,"indent":2,"parameters":[]},{"code":121,"indent":2,"parameters":[3,3,1]},{"code":0,"indent":2,"parameters":[]},{"code":411,"indent":1,"parameters":[]},{"code":250,"indent":2,"parameters":[{"name":"ter1","volume":15,"pitch":90,"pan":0}]},{"code":0,"indent":2,"parameters":[]},{"code":412,"indent":1,"parameters":[]},{"code":121,"indent":1,"parameters":[3,3,1]},{"code":0,"indent":1,"parameters":[]},{"code":411,"indent":0,"parameters":[]},{"code":250,"indent":1,"parameters":[{"name":"ter2","volume":15,"pitch":90,"pan":0}]},{"code":0,"indent":1,"parameters":[]},{"code":412,"indent":0,"parameters":[]},{"code":121,"indent":0,"parameters":[3,3,1]},{"code":0,"indent":0,"parameters":[]}],"name":"PisoTerra","switchId":3,"trigger":2},
{"id":3,"list":[{"code":122,"indent":0,"parameters":[1,20,0,2,1,20]},{"code":111,"indent":0,"parameters":[1,1,0,5,3]},{"code":111,"indent":1,"parameters":[1,1,0,10,3]},{"code":111,"indent":2,"parameters":[1,1,0,15,3]},{"code":250,"indent":3,"parameters":[{"name":"grama1","volume":20,"pitch":110,"pan":0}]},{"code":0,"indent":3,"parameters":[]},{"code":411,"indent":2,"parameters":[]},{"code":250,"indent":3,"parameters":[{"name":"grama1","volume":20,"pitch":100,"pan":0}]},{"code":0,"indent":3,"parameters":[]},{"code":412,"indent":2,"parameters":[]},{"code":121,"indent":2,"parameters":[3,3,1]},{"code":0,"indent":2,"parameters":[]},{"code":411,"indent":1,"parameters":[]},{"code":250,"indent":2,"parameters":[{"name":"grama2","volume":15,"pitch":90,"pan":0}]},{"code":0,"indent":2,"parameters":[]},{"code":412,"indent":1,"parameters":[]},{"code":121,"indent":1,"parameters":[3,3,1]},{"code":0,"indent":1,"parameters":[]},{"code":411,"indent":0,"parameters":[]},{"code":250,"indent":1,"parameters":[{"name":"grama2","volume":20,"pitch":90,"pan":0}]},{"code":0,"indent":1,"parameters":[]},{"code":412,"indent":0,"parameters":[]},{"code":121,"indent":0,"parameters":[3,3,1]},{"code":0,"indent":0,"parameters":[]}],"name":"PisoGrama","switchId":3,"trigger":2},
{"id":4,"list":[{"code":122,"indent":0,"parameters":[1,20,0,2,1,20]},{"code":111,"indent":0,"parameters":[1,1,0,5,3]},{"code":111,"indent":1,"parameters":[1,1,0,10,3]},{"code":111,"indent":2,"parameters":[1,1,0,15,3]},{"code":250,"indent":3,"parameters":[{"name":"mad1","volume":20,"pitch":110,"pan":0}]},{"code":0,"indent":3,"parameters":[]},{"code":411,"indent":2,"parameters":[]},{"code":250,"indent":3,"parameters":[{"name":"mad1","volume":20,"pitch":100,"pan":0}]},{"code":0,"indent":3,"parameters":[]},{"code":412,"indent":2,"parameters":[]},{"code":121,"indent":2,"parameters":[3,3,1]},{"code":0,"indent":2,"parameters":[]},{"code":411,"indent":1,"parameters":[]},{"code":250,"indent":2,"parameters":[{"name":"mad1","volume":15,"pitch":90,"pan":0}]},{"code":0,"indent":2,"parameters":[]},{"code":412,"indent":1,"parameters":[]},{"code":121,"indent":1,"parameters":[3,3,1]},{"code":0,"indent":1,"parameters":[]},{"code":411,"indent":0,"parameters":[]},{"code":250,"indent":1,"parameters":[{"name":"mad2","volume":20,"pitch":90,"pan":0}]},{"code":0,"indent":1,"parameters":[]},{"code":412,"indent":0,"parameters":[]},{"code":121,"indent":0,"parameters":[3,3,1]},{"code":0,"indent":0,"parameters":[]}],"name":"PisoGrama","switchId":3,"trigger":2},
{"id":5,"list":[{"code":122,"indent":0,"parameters":[1,20,0,2,1,20]},{"code":111,"indent":0,"parameters":[1,1,0,5,3]},{"code":111,"indent":1,"parameters":[1,1,0,10,3]},{"code":111,"indent":2,"parameters":[1,1,0,15,3]},{"code":250,"indent":3,"parameters":[{"name":"mad1","volume":20,"pitch":110,"pan":0}]},{"code":0,"indent":3,"parameters":[]},{"code":411,"indent":2,"parameters":[]},{"code":250,"indent":3,"parameters":[{"name":"mad1","volume":20,"pitch":100,"pan":0}]},{"code":0,"indent":3,"parameters":[]},{"code":412,"indent":2,"parameters":[]},{"code":121,"indent":2,"parameters":[3,3,1]},{"code":0,"indent":2,"parameters":[]},{"code":411,"indent":1,"parameters":[]},{"code":250,"indent":2,"parameters":[{"name":"mad1","volume":15,"pitch":90,"pan":0}]},{"code":0,"indent":2,"parameters":[]},{"code":412,"indent":1,"parameters":[]},{"code":121,"indent":1,"parameters":[3,3,1]},{"code":0,"indent":1,"parameters":[]},{"code":411,"indent":0,"parameters":[]},{"code":250,"indent":1,"parameters":[{"name":"mad2","volume":20,"pitch":90,"pan":0}]},{"code":0,"indent":1,"parameters":[]},{"code":412,"indent":0,"parameters":[]},{"code":121,"indent":0,"parameters":[3,3,1]},{"code":0,"indent":0,"parameters":[]}],"name":"PisoMadeira","switchId":3,"trigger":2},
{"id":6,"list":[{"code":122,"indent":0,"parameters":[1,20,0,2,1,20]},{"code":111,"indent":0,"parameters":[1,1,0,5,3]},{"code":111,"indent":1,"parameters":[1,1,0,10,3]},{"code":111,"indent":2,"parameters":[1,1,0,15,3]},{"code":250,"indent":3,"parameters":[{"name":"mad1","volume":20,"pitch":110,"pan":0}]},{"code":0,"indent":3,"parameters":[]},{"code":411,"indent":2,"parameters":[]},{"code":250,"indent":3,"parameters":[{"name":"mad1","volume":20,"pitch":100,"pan":0}]},{"code":0,"indent":3,"parameters":[]},{"code":412,"indent":2,"parameters":[]},{"code":121,"indent":2,"parameters":[3,3,1]},{"code":0,"indent":2,"parameters":[]},{"code":411,"indent":1,"parameters":[]},{"code":250,"indent":2,"parameters":[{"name":"mad1","volume":15,"pitch":90,"pan":0}]},{"code":0,"indent":2,"parameters":[]},{"code":412,"indent":1,"parameters":[]},{"code":121,"indent":1,"parameters":[3,3,1]},{"code":0,"indent":1,"parameters":[]},{"code":411,"indent":0,"parameters":[]},{"code":250,"indent":1,"parameters":[{"name":"mad2","volume":20,"pitch":90,"pan":0}]},{"code":0,"indent":1,"parameters":[]},{"code":412,"indent":0,"parameters":[]},{"code":121,"indent":0,"parameters":[3,3,1]},{"code":0,"indent":0,"parameters":[]}],"name":"PisoMadeira","switchId":3,"trigger":2},
{"id":7,"list":[{"code":122,"indent":0,"parameters":[1,20,0,2,1,20]},{"code":111,"indent":0,"parameters":[1,1,0,5,3]},{"code":111,"indent":1,"parameters":[1,1,0,10,3]},{"code":111,"indent":2,"parameters":[1,1,0,15,3]},{"code":250,"indent":3,"parameters":[{"name":"mad1","volume":20,"pitch":110,"pan":0}]},{"code":0,"indent":3,"parameters":[]},{"code":411,"indent":2,"parameters":[]},{"code":250,"indent":3,"parameters":[{"name":"mad1","volume":20,"pitch":100,"pan":0}]},{"code":0,"indent":3,"parameters":[]},{"code":412,"indent":2,"parameters":[]},{"code":121,"indent":2,"parameters":[3,3,1]},{"code":0,"indent":2,"parameters":[]},{"code":411,"indent":1,"parameters":[]},{"code":250,"indent":2,"parameters":[{"name":"mad1","volume":15,"pitch":90,"pan":0}]},{"code":0,"indent":2,"parameters":[]},{"code":412,"indent":1,"parameters":[]},{"code":121,"indent":1,"parameters":[3,3,1]},{"code":0,"indent":1,"parameters":[]},{"code":411,"indent":0,"parameters":[]},{"code":250,"indent":1,"parameters":[{"name":"mad2","volume":20,"pitch":90,"pan":0}]},{"code":0,"indent":1,"parameters":[]},{"code":412,"indent":0,"parameters":[]},{"code":121,"indent":0,"parameters":[3,3,1]},{"code":0,"indent":0,"parameters":[]}],"name":"PisoMadeira","switchId":3,"trigger":2},
{"id":8,"list":[{"code":122,"indent":0,"parameters":[1,20,0,2,1,20]},{"code":111,"indent":0,"parameters":[1,1,0,5,3]},{"code":111,"indent":1,"parameters":[1,1,0,10,3]},{"code":111,"indent":2,"parameters":[1,1,0,15,3]},{"code":250,"indent":3,"parameters":[{"name":"mad1","volume":20,"pitch":110,"pan":0}]},{"code":0,"indent":3,"parameters":[]},{"code":411,"indent":2,"parameters":[]},{"code":250,"indent":3,"parameters":[{"name":"mad1","volume":20,"pitch":100,"pan":0}]},{"code":0,"indent":3,"parameters":[]},{"code":412,"indent":2,"parameters":[]},{"code":121,"indent":2,"parameters":[3,3,1]},{"code":0,"indent":2,"parameters":[]},{"code":411,"indent":1,"parameters":[]},{"code":250,"indent":2,"parameters":[{"name":"mad1","volume":15,"pitch":90,"pan":0}]},{"code":0,"indent":2,"parameters":[]},{"code":412,"indent":1,"parameters":[]},{"code":121,"indent":1,"parameters":[3,3,1]},{"code":0,"indent":1,"parameters":[]},{"code":411,"indent":0,"parameters":[]},{"code":250,"indent":1,"parameters":[{"name":"mad2","volume":20,"pitch":90,"pan":0}]},{"code":0,"indent":1,"parameters":[]},{"code":412,"indent":0,"parameters":[]},{"code":121,"indent":0,"parameters":[3,3,1]},{"code":0,"indent":0,"parameters":[]}],"name":"PisoMadeira","switchId":3,"trigger":2},
{"id":9,"list":[{"code":122,"indent":0,"parameters":[1,20,0,2,1,20]},{"code":111,"indent":0,"parameters":[1,1,0,5,3]},{"code":111,"indent":1,"parameters":[1,1,0,10,3]},{"code":111,"indent":2,"parameters":[1,1,0,15,3]},{"code":250,"indent":3,"parameters":[{"name":"mad1","volume":20,"pitch":110,"pan":0}]},{"code":0,"indent":3,"parameters":[]},{"code":411,"indent":2,"parameters":[]},{"code":250,"indent":3,"parameters":[{"name":"mad1","volume":20,"pitch":100,"pan":0}]},{"code":0,"indent":3,"parameters":[]},{"code":412,"indent":2,"parameters":[]},{"code":121,"indent":2,"parameters":[3,3,1]},{"code":0,"indent":2,"parameters":[]},{"code":411,"indent":1,"parameters":[]},{"code":250,"indent":2,"parameters":[{"name":"mad1","volume":15,"pitch":90,"pan":0}]},{"code":0,"indent":2,"parameters":[]},{"code":412,"indent":1,"parameters":[]},{"code":121,"indent":1,"parameters":[3,3,1]},{"code":0,"indent":1,"parameters":[]},{"code":411,"indent":0,"parameters":[]},{"code":250,"indent":1,"parameters":[{"name":"mad2","volume":20,"pitch":90,"pan":0}]},{"code":0,"indent":1,"parameters":[]},{"code":412,"indent":0,"parameters":[]},{"code":121,"indent":0,"parameters":[3,3,1]},{"code":0,"indent":0,"parameters":[]}],"name":"PisoMadeira","switchId":3,"trigger":2},
{"id":10,"list":[{"code":122,"indent":0,"parameters":[1,20,0,2,1,20]},{"code":111,"indent":0,"parameters":[1,1,0,5,3]},{"code":111,"indent":1,"parameters":[1,1,0,10,3]},{"code":111,"indent":2,"parameters":[1,1,0,15,3]},{"code":250,"indent":3,"parameters":[{"name":"mad1","volume":20,"pitch":110,"pan":0}]},{"code":0,"indent":3,"parameters":[]},{"code":411,"indent":2,"parameters":[]},{"code":250,"indent":3,"parameters":[{"name":"mad1","volume":20,"pitch":100,"pan":0}]},{"code":0,"indent":3,"parameters":[]},{"code":412,"indent":2,"parameters":[]},{"code":121,"indent":2,"parameters":[3,3,1]},{"code":0,"indent":2,"parameters":[]},{"code":411,"indent":1,"parameters":[]},{"code":250,"indent":2,"parameters":[{"name":"mad1","volume":15,"pitch":90,"pan":0}]},{"code":0,"indent":2,"parameters":[]},{"code":412,"indent":1,"parameters":[]},{"code":121,"indent":1,"parameters":[3,3,1]},{"code":0,"indent":1,"parameters":[]},{"code":411,"indent":0,"parameters":[]},{"code":250,"indent":1,"parameters":[{"name":"mad2","volume":20,"pitch":90,"pan":0}]},{"code":0,"indent":1,"parameters":[]},{"code":412,"indent":0,"parameters":[]},{"code":121,"indent":0,"parameters":[3,3,1]},{"code":0,"indent":0,"parameters":[]}],"name":"PisoMadeira","switchId":3,"trigger":2},
{"id":11,"list":[{"code":0,"indent":0,"parameters":[]}],"name":"","switchId":1,"trigger":0}
]